she_codes_uv_example/__init__.py
she_codes_uv_example/cli.py
she_codes_uv_example-0.1.3.dist-info/METADATA
she_codes_uv_example-0.1.3.dist-info/WHEEL
she_codes_uv_example-0.1.3.dist-info/entry_points.txt
she_codes_uv_example-0.1.3.dist-info/top_level.txt
she_codes_uv_example-0.1.3.dist-info/RECORD
