Metadata-Version: 2.4
Name: she-codes-uv-example
Version: 0.1.3
Summary: Example package deployment
Author-email: Oliver Lavers <hauteclere.code@gmail.com>
Requires-Python: >=3.9
Requires-Dist: cowsay>=6.1
